{
"in": ["Indonesian"],
"iw": ["Hebrew"],
"ji": ["Yiddish"],
"jw": ["Javanese"],
"mo": ["Moldavian", "Moldovan"],
"aam": ["Aramanik"],
"adp": ["Adap"],
"agp": ["Paranan"],
"ais": ["Nataoran Amis"],
"aoh": ["Arma"],
"asd": ["Asas"],
"aue": ["ǂKxʼauǁʼein"],
"ayx": ["Ayi (China)"],
"ayy": ["Tayabas Ayta"],
"baz": ["Tunen"],
"bbz": ["Babalia Creole Arabic"],
"bgm": ["Baga Mboteni"],
"bhk": ["Albay Bicolano"],
"bjd": ["Bandjigali"],
"bjq": ["Southern Betsimisaraka Malagasy"],
"bkb": ["Finallig"],
"bmy": ["Bemba (Democratic Republic of Congo)"],
"bpb": ["Barbacoas"],
"btb": ["Beti (Cameroon)"],
"btl": ["Bhatola"],
"bxx": ["Borna (Democratic Republic of Congo)"],
"byy": ["Buya"],
"cbe": ["Chipiajes"],
"cbh": ["Cagua"],
"cca": ["Cauca"],
"ccq": ["Chaungtha"],
"cdg": ["Chamari"],
"cjr": ["Chorotega"],
"cka": ["Khumi Awa Chin"],
"cmk": ["Chimakum"],
"coy": ["Coyaima"],
"cqu": ["Chilean Quechua"],
"cum": ["Cumeral"],
"daf": ["Dan"],
"dap": ["Nisi (India)"],
"dgu": ["Degaru"],
"dha": ["Dhanwar (India)"],
"dit": ["Dirari"],
"djl": ["Djiwarli"],
"dkl": ["Kolum So Dogon"],
"drh": ["Darkhat"],
"drr": ["Dororo"],
"drw": ["Darwazi"],
"dud": ["Hun-Saare"],
"duj": ["Dhuwal"],
"dwl": ["Walo Kumbe Dogon"],
"dzd": ["Daza"],
"ekc": ["Eastern Karnic"],
"elp": ["Elpaputih"],
"emo": ["Emok"],
"gav": ["Gabutamon"],
"gbc": ["Garawa"],
"gfx": ["Mangetti Dune ǃXung"],
"ggn": ["Eastern Gurung"],
"ggo": ["Southern Gondi"],
"ggr": ["Aghu Tharnggalu"],
"gio": ["Gelao"],
"gli": ["Guliguli"],
"gti": ["Gbati-ri"],
"guv": ["Gey"],
"hrr": ["Horuru"],
"iap": ["Iapama"],
"ibi": ["Ibilo"],
"ill": ["Iranun"],
"ilw": ["Talur"],
"ime": ["Imeraguen"],
"izi": ["Izi-Ezaa-Ikwo-Mgbo"],
"jar": ["Jarawa (Nigeria)"],
"jeg": ["Jeng"],
"kbf": ["Kakauhua"],
"kdv": ["Kado"],
"kgc": ["Kasseng"],
"kgd": ["Kataang"],
"kgh": ["Upper Tanudan Kalinga"],
"kjf": ["Khalaj [Indo-Iranian]"],
"koj": ["Sara Dunjo"],
"kox": ["Coxima"],
"kpp": ["Paku Karen"],
"krm": ["Krim"],
"ktr": ["Kota Marudu Tinagas"],
"kvs": ["Kunggara"],
"kwq": ["Kwak"],
"kxe": ["Kakihum"],
"kxl": ["Nepali Kurux"],
"kxu": ["Kui (India)"],
"kzh": ["Kenuzi-Dongola"],
"kzj": ["Coastal Kadazan"],
"kzt": ["Tambunan Dusun"],
"lba": ["Lui"],
"leg": ["Lengua"],
"lii": ["Lingkhim"],
"llo": ["Khlor"],
"lmm": ["Lamam"],
"lmz": ["Lumbee"],
"lsg": ["Lyons Sign Language"],
"meg": ["Mea"],
"mgx": ["Omati"],
"mhh": ["Maskoy Pidgin"],
"mja": ["Mahei"],
"mld": ["Malakhel"],
"mnt": ["Maykulan"],
"mof": ["Mohegan-Montauk-Narragansett"],
"mst": ["Cataelano Mandaya"],
"mwd": ["Mudbura"],
"mwj": ["Maligo"],
"mwx": ["Mediak"],
"mwy": ["Mosiro"],
"myd": ["Maramba"],
"myi": ["Mina (India)"],
"myq": ["Forest Maninka"],
"myt": ["Sangab Mandaya"],
"nad": ["Nijadali"],
"nbf": ["Naxi"],
"nbx": ["Ngura"],
"ncp": ["Ndaktup"],
"nln": ["Durango Nahuatl"],
"nlr": ["Ngarla"],
"nns": ["Ningye"],
"nnx": ["Ngong"],
"noo": ["Nootka"],
"nts": ["Natagaimas"],
"nxu": ["Narau"],
"ome": ["Omejes"],
"oun": ["ǃOǃung"],
"pbz": ["Palu"],
"pcr": ["Panang"],
"pgy": ["Pongyong"],
"plp": ["Palpa"],
"pmc": ["Palumata"],
"pmu": ["Mirpur Panjabi"],
"pod": ["Ponares"],
"ppa": ["Pao"],
"ppr": ["Piru"],
"prb": ["Lua'"],
"pry": ["Pray 3"],
"puk": ["Pu Ko"],
"puz": ["Purum Naga"],
"rie": ["Rien"],
"rmr": ["Caló"],
"rna": ["Runa"],
"rsi": ["Rennellese Sign Language"],
"sap": ["Sanapaná"],
"sca": ["Sansu"],
"sdm": ["Semandang"],
"sgl": ["Sanglechi-Ishkashimi"],
"sgo": ["Songa"],
"skk": ["Sok"],
"snh": ["Shinabo"],
"sul": ["Surigaonon"],
"sum": ["Sumo-Mayangna"],
"svr": ["Savara"],
"tbb": ["Tapeba"],
"tdu": ["Tempasuk Dusun"],
"tgg": ["Tangga"],
"thc": ["Tai Hang Tong"],
"thw": ["Thudam"],
"thx": ["The"],
"tid": ["Tidong"],
"tie": ["Tingal"],
"tkk": ["Takpa"],
"tlw": ["South Wemale"],
"tmp": ["Tai Mène"],
"tne": ["Tinoc Kallahan"],
"tnf": ["Tangshewi"],
"toe": ["Tomedes"],
"tsf": ["Southwestern Tamang"],
"unp": ["Worora"],
"uok": ["Uokha"],
"wgw": ["Wagawaga"],
"wit": ["Wintu"],
"wiw": ["Wirangu"],
"xba": ["Kamba (Brazil)"],
"xbx": ["Kabixí"],
"xia": ["Xiandao"],
"xip": ["Xipináwa"],
"xkh": ["Karahawyana"],
"xrq": ["Karranga"],
"xtz": ["Tasmanian"],
"ybd": ["Yangbye"],
"yds": ["Yiddish Sign Language"],
"yen": ["Yendang"],
"yiy": ["Yir Yoront"],
"yma": ["Yamphe"],
"ymt": ["Mator-Taygi-Karagas"],
"ynh": ["Yangho"],
"yos": ["Yos"],
"yri": ["Yarí"],
"yuu": ["Yugh"],
"zir": ["Ziriya"]
}